theforensicator/__init__.py
theforensicator/app.py
theforensicator/artefacts/browser_chrome.yaml
theforensicator/artefacts/browser_edge.yaml
theforensicator/artefacts/browser_firefox.yaml
theforensicator/artefacts/browser_ie.yaml
theforensicator/artefacts/events_logs.yaml
theforensicator/artefacts/prefetch.yaml
theforensicator/artefacts/registry_system.yaml
theforensicator/artefacts/registry_user.yaml
theforensicator/cli.py
theforensicator/ewf/__init__.py
theforensicator/ewf/file_parsing.py
theforensicator/fs/__init__.py
theforensicator/fs/defs.py
theforensicator/fs/gpt.py
theforensicator/fs/mbr.py
theforensicator/fs/ntfs.py
theforensicator-0.1.6.dist-info/LICENSE
theforensicator-0.1.6.dist-info/METADATA
theforensicator-0.1.6.dist-info/WHEEL
theforensicator-0.1.6.dist-info/entry_points.txt
theforensicator-0.1.6.dist-info/RECORD
